{
    "description": "pyrite (optimised using PBE)",
    "cell": {
        "array": {
            "__ndarray__": [
                [
                    3,
                    3
                ],
                "float64",
                [
                    5.38932639,
                    0.0,
                    3.30001065653693e-16,
                    -3.30001065653693e-16,
                    5.38932639,
                    3.30001065653693e-16,
                    0.0,
                    0.0,
                    5.38932639
                ]
            ]
        },
        "pbc": {
            "__ndarray__": [
                [
                    3
                ],
                "bool",
                [
                    true,
                    true,
                    true
                ]
            ]
        },
        "__ase_objtype__": "cell"
    },
    "arrays": {
        "numbers": {
            "__ndarray__": [
                [
                    12
                ],
                "int64",
                [
                    26,
                    26,
                    26,
                    26,
                    16,
                    16,
                    16,
                    16,
                    16,
                    16,
                    16,
                    16
                ]
            ]
        },
        "positions": {
            "__ndarray__": [
                [
                    12,
                    3
                ],
                "float64",
                [
                    -4.74318190561602e-19,
                    0.0,
                    -2.9043612692431513e-35,
                    -2.6946631940827364,
                    0.0,
                    -2.6946631940827364,
                    -2.6946631940827364,
                    -2.6946631940827364,
                    -3.300010655413606e-16,
                    1.645262145801187e-16,
                    -2.6946631940827364,
                    -2.6946631940827364,
                    2.0490080790160476,
                    2.0490080790160476,
                    2.049008079016048,
                    0.6456551171081659,
                    -2.0490080790160476,
                    -0.6456551171081659,
                    -0.6456551171081658,
                    0.6456551171081658,
                    -2.0490080790160476,
                    -2.0490080790160476,
                    -0.6456551171081658,
                    0.6456551171081657,
                    -2.0490080790160476,
                    -2.0490080790160476,
                    -2.049008079016048,
                    -0.6456551171081659,
                    2.0490080790160476,
                    0.6456551171081659,
                    0.6456551171081658,
                    -0.6456551171081658,
                    2.0490080790160476,
                    2.0490080790160476,
                    0.6456551171081658,
                    -0.6456551171081657
                ]
            ]
        }
    },
    "info": {},
    "constraints": [],
    "celldisp": {
        "__ndarray__": [
            [
                3,
                1
            ],
            "float64",
            [
                0.0,
                0.0,
                0.0
            ]
        ]
    },
    "calculator": null
}
